{
  "title": "Farting Through Dubai",
  "synopsis": "Join Roey as he hilariously navigates a Dubai plumbing disaster through the power of farting!",
  "name": "Roey Levartovsky",
  "gender": "male",
  "page_count": 6,
  "theme": "Pixar 3D animated cartoon style",
  "user_answers_list": {
    "What is Roey's job?": "plumber",
    "What is Roey's dream?": "farting",
    "What is Roey's hobby?": "dancing in the rain",
    "What is Roey's catchphrase?": "it is not me! its my dark side!",
    "What is Roey's favorite place?": "Dubai",
    "What is Roey's taste in women?": "blonde in bikini"
  }
}
